{
	"pattrstorage" : 	{
		"name" : "bay_storage",
		"slots" : 		{
			"1" : 			{
				"id" : 1,
				"data" : 				{
					"matrix_counts2values" : [ 0, 0, 1.0, 1, 1, 1.0 ],
					"steps" : [ 4 ],
					"sliders_select" : [ "divs" ],
					"sliders_select[1]" : [ "outers" ],
					"divs_sliders::sliders" : [ 4, 2, 4, 5 ],
					"ratios_sliders::sliders" : [ 1, 1, 2, 2 ],
					"outer_times::mode" : [ "bbu" ],
					"outer_times::scale" : [ 1.0 ],
					"outer_times::bbu" : [ 1, 4, 0 ],
					"outer_times::ms" : [ 1000.0 ],
					"outer_times::notevalues" : [ "1n" ],
					"inner_times::mode" : [ "fit" ],
					"inner_times::scale" : [ 1.0 ],
					"inner_times::bbu" : [ 1, 0, 0 ],
					"inner_times::ms" : [ 1000.0 ],
					"inner_times::notevalues" : [ "1n" ],
					"values_1::sliders_select" : [ "notes" ],
					"values_1::notes_sliders::steps" : [ 4 ],
					"values_1::notes_sliders::sliders" : [ 0, 1, 2, 4 ],
					"values_1::velocities_sliders::steps" : [ 1 ],
					"values_1::velocities_sliders::sliders" : [ 1.0 ],
					"values_1::event_duration::mode" : [ "fit.outer" ],
					"values_1::event_duration::scale" : [ 1.0 ],
					"values_1::event_duration::bbu" : [ 1, 0, 0 ],
					"values_1::event_duration::ms" : [ 1000.0 ],
					"values_1::event_duration::notevalues" : [ "1n" ],
					"values_1[1]::sliders_select" : [ "notes" ],
					"values_1[1]::notes_sliders::steps" : [ 2 ],
					"values_1[1]::notes_sliders::sliders" : [ 3, 8 ],
					"values_1[1]::velocities_sliders::steps" : [ 1 ],
					"values_1[1]::velocities_sliders::sliders" : [ 1.0 ],
					"values_1[1]::event_duration::mode" : [ "fit.inner" ],
					"values_1[1]::event_duration::scale" : [ 1.0 ],
					"values_1[1]::event_duration::bbu" : [ 1, 0, 0 ],
					"values_1[1]::event_duration::ms" : [ 1000.0 ],
					"values_1[1]::event_duration::notevalues" : [ "1n" ]
				}

			}
,
			"2" : 			{
				"id" : 2,
				"data" : 				{
					"matrix_counts2values" : [ 0, 0, 1.0, 1, 1, 1.0 ],
					"steps" : [ 4 ],
					"sliders_select" : [ "divs" ],
					"sliders_select[1]" : [ "outers" ],
					"divs_sliders::sliders" : [ 4, 2, 4, 5 ],
					"ratios_sliders::sliders" : [ 1, 1, 2, 2 ],
					"outer_times::mode" : [ "bbu" ],
					"outer_times::scale" : [ 1.0 ],
					"outer_times::bbu" : [ 1, 4, 0 ],
					"outer_times::ms" : [ 1000.0 ],
					"outer_times::notevalues" : [ "1n" ],
					"inner_times::mode" : [ "fit" ],
					"inner_times::scale" : [ 1.0 ],
					"inner_times::bbu" : [ 1, 0, 0 ],
					"inner_times::ms" : [ 1000.0 ],
					"inner_times::notevalues" : [ "1n" ],
					"values_1::sliders_select" : [ "notes" ],
					"values_1::notes_sliders::steps" : [ 4 ],
					"values_1::notes_sliders::sliders" : [ 0, 1, 2, 4 ],
					"values_1::velocities_sliders::steps" : [ 1 ],
					"values_1::velocities_sliders::sliders" : [ 1.0 ],
					"values_1::event_duration::mode" : [ "fit.outer" ],
					"values_1::event_duration::scale" : [ 1.0 ],
					"values_1::event_duration::bbu" : [ 1, 0, 0 ],
					"values_1::event_duration::ms" : [ 1000.0 ],
					"values_1::event_duration::notevalues" : [ "1n" ],
					"values_1[1]::sliders_select" : [ "notes" ],
					"values_1[1]::notes_sliders::steps" : [ 2 ],
					"values_1[1]::notes_sliders::sliders" : [ 3, 8 ],
					"values_1[1]::velocities_sliders::steps" : [ 1 ],
					"values_1[1]::velocities_sliders::sliders" : [ 1.0 ],
					"values_1[1]::event_duration::mode" : [ "fit.inner" ],
					"values_1[1]::event_duration::scale" : [ 1.0 ],
					"values_1[1]::event_duration::bbu" : [ 1, 0, 0 ],
					"values_1[1]::event_duration::ms" : [ 1000.0 ],
					"values_1[1]::event_duration::notevalues" : [ "1n" ]
				}

			}
,
			"3" : 			{
				"id" : 3,
				"data" : 				{
					"matrix_counts2values" : [ 0, 0, 1.0, 1, 1, 1.0 ],
					"steps" : [ 4 ],
					"sliders_select" : [ "divs" ],
					"sliders_select[1]" : [ "outers" ],
					"divs_sliders::sliders" : [ 2, 4, 2, 5 ],
					"ratios_sliders::sliders" : [ 1, 1, 2, 2 ],
					"outer_times::mode" : [ "bbu" ],
					"outer_times::scale" : [ 1.0 ],
					"outer_times::bbu" : [ 0, 3, 0 ],
					"outer_times::ms" : [ 1000.0 ],
					"outer_times::notevalues" : [ "1n" ],
					"inner_times::mode" : [ "notevalues" ],
					"inner_times::scale" : [ 1.0 ],
					"inner_times::bbu" : [ 1, 0, 0 ],
					"inner_times::ms" : [ 1000.0 ],
					"inner_times::notevalues" : [ "16n" ],
					"values_1::sliders_select" : [ "notes" ],
					"values_1::notes_sliders::steps" : [ 4 ],
					"values_1::notes_sliders::sliders" : [ 0, 0, 0, 0 ],
					"values_1::velocities_sliders::steps" : [ 1 ],
					"values_1::velocities_sliders::sliders" : [ 1.0 ],
					"values_1::event_duration::mode" : [ "fit.outer" ],
					"values_1::event_duration::scale" : [ 1.0 ],
					"values_1::event_duration::bbu" : [ 1, 0, 0 ],
					"values_1::event_duration::ms" : [ 1000.0 ],
					"values_1::event_duration::notevalues" : [ "1n" ],
					"values_1[1]::sliders_select" : [ "notes" ],
					"values_1[1]::notes_sliders::steps" : [ 3 ],
					"values_1[1]::notes_sliders::sliders" : [ 2, 2, 2 ],
					"values_1[1]::velocities_sliders::steps" : [ 1 ],
					"values_1[1]::velocities_sliders::sliders" : [ 1.0 ],
					"values_1[1]::event_duration::mode" : [ "fit.inner" ],
					"values_1[1]::event_duration::scale" : [ 1.0 ],
					"values_1[1]::event_duration::bbu" : [ 1, 0, 0 ],
					"values_1[1]::event_duration::ms" : [ 1000.0 ],
					"values_1[1]::event_duration::notevalues" : [ "1n" ]
				}

			}
,
			"4" : 			{
				"id" : 4,
				"data" : 				{
					"matrix_counts2values" : [ 1, 1, 1.0 ],
					"steps" : [ 2 ],
					"sliders_select" : [ "divs" ],
					"sliders_select[1]" : [ "inners" ],
					"divs_sliders::sliders" : [ 3, 6 ],
					"ratios_sliders::sliders" : [ 1, 2 ],
					"outer_times::mode" : [ "fit" ],
					"outer_times::scale" : [ 1.0 ],
					"outer_times::bbu" : [ 1, 0, 0 ],
					"outer_times::ms" : [ 1000.0 ],
					"outer_times::notevalues" : [ "1n" ],
					"inner_times::mode" : [ "notevalues" ],
					"inner_times::scale" : [ 1.0 ],
					"inner_times::bbu" : [ 1, 0, 0 ],
					"inner_times::ms" : [ 1000.0 ],
					"inner_times::notevalues" : [ "8n" ],
					"values_1::sliders_select" : [ "notes" ],
					"values_1::notes_sliders::steps" : [ 1 ],
					"values_1::notes_sliders::sliders" : [ 0 ],
					"values_1::velocities_sliders::steps" : [ 1 ],
					"values_1::velocities_sliders::sliders" : [ 1.0 ],
					"values_1::event_duration::mode" : [ "fit.outer" ],
					"values_1::event_duration::scale" : [ 1.0 ],
					"values_1::event_duration::bbu" : [ 1, 0, 0 ],
					"values_1::event_duration::ms" : [ 1000.0 ],
					"values_1::event_duration::notevalues" : [ "1n" ],
					"values_1[1]::sliders_select" : [ "notes" ],
					"values_1[1]::notes_sliders::steps" : [ 1 ],
					"values_1[1]::notes_sliders::sliders" : [ 0 ],
					"values_1[1]::velocities_sliders::steps" : [ 1 ],
					"values_1[1]::velocities_sliders::sliders" : [ 1.0 ],
					"values_1[1]::event_duration::mode" : [ "fit.outer" ],
					"values_1[1]::event_duration::scale" : [ 1.0 ],
					"values_1[1]::event_duration::bbu" : [ 1, 0, 0 ],
					"values_1[1]::event_duration::ms" : [ 1000.0 ],
					"values_1[1]::event_duration::notevalues" : [ "1n" ]
				}

			}

		}

	}

}
